LICENSE
README.md
setup.py
pfg/__init__.py
pfg/factor_graph.py
pfg.egg-info/PKG-INFO
pfg.egg-info/SOURCES.txt
pfg.egg-info/dependency_links.txt
pfg.egg-info/requires.txt
pfg.egg-info/top_level.txt