Metadata-Version: 2.1
Name: pfg
Version: 1.0.1
Summary: A lightweight library for building Factor Graphs and performing inference using the loopy belief propagation algorithm.
Home-page: https://github.com/steveschwarcz/PFG-Python-Factor-Graph-Library
Author: Steven Schwarcz
Author-email: sasz11@gmail.com
License: UNKNOWN
Platform: UNKNOWN
Classifier: Programming Language :: Python :: 3
Classifier: License :: OSI Approved :: MIT License
Classifier: Operating System :: OS Independent
